{
    "mal_id": 11284,
    "url": "https://myanimelist.net/people/11284/Shintarou_Inokawa",
    "image_url": "https://cdn.myanimelist.net/img/sp/icon/apple-touch-icon-256.png",
    "name": "Shintarou Inokawa",
    "given_name": "慎太郎",
    "family_name": "井之川",
    "birthday": null,
    "member_favorites": 7,
    "voice_acting_roles": [],
    "anime_staff_positions": [
        {
            "position": "Director",
            "anime": {
                "mal_id": 1055,
                "url": "https://myanimelist.net/anime/1055/Blame",
                "image_url": "https://cdn.myanimelist.net/images/anime/2/2713.jpg?s=315529ae08d443003c94d132c33beb84",
                "name": "Blame!"
            }
        },
        {
            "position": "Storyboard",
            "anime": {
                "mal_id": 34566,
                "url": "https://myanimelist.net/anime/34566/Boruto__Naruto_Next_Generations",
                "image_url": "https://cdn.myanimelist.net/images/anime/9/84460.jpg?s=e4439268efbe43e56433d9fa009e5974",
                "name": "Boruto: Naruto Next Generations"
            }
        },
        {
            "position": "Storyboard",
            "anime": {
                "mal_id": 1678,
                "url": "https://myanimelist.net/anime/1678/Cyborg_009__The_Cyborg_Soldier",
                "image_url": "https://cdn.myanimelist.net/images/anime/5/21620.jpg?s=759c3ea7d9dd65d7c75bbc0ad99ffad8",
                "name": "Cyborg 009: The Cyborg Soldier"
            }
        },
        {
            "position": "Episode Director",
            "anime": {
                "mal_id": 1678,
                "url": "https://myanimelist.net/anime/1678/Cyborg_009__The_Cyborg_Soldier",
                "image_url": "https://cdn.myanimelist.net/images/anime/5/21620.jpg?s=759c3ea7d9dd65d7c75bbc0ad99ffad8",
                "name": "Cyborg 009: The Cyborg Soldier"
            }
        },
        {
            "position": "Storyboard",
            "anime": {
                "mal_id": 2907,
                "url": "https://myanimelist.net/anime/2907/Cyborg_Kuro-chan",
                "image_url": "https://cdn.myanimelist.net/images/anime/11/17464.jpg?s=580dcfd00c88d8a58e86e779faabc366",
                "name": "Cyborg Kuro-chan"
            }
        },
        {
            "position": "Episode Director",
            "anime": {
                "mal_id": 2907,
                "url": "https://myanimelist.net/anime/2907/Cyborg_Kuro-chan",
                "image_url": "https://cdn.myanimelist.net/images/anime/11/17464.jpg?s=580dcfd00c88d8a58e86e779faabc366",
                "name": "Cyborg Kuro-chan"
            }
        },
        {
            "position": "Storyboard",
            "anime": {
                "mal_id": 1684,
                "url": "https://myanimelist.net/anime/1684/Dotto_Koni-chan",
                "image_url": "https://cdn.myanimelist.net/images/anime/1910/106998.jpg?s=28ef6c6275889a5054e640f11e7c9526",
                "name": "Dotto Koni-chan"
            }
        },
        {
            "position": "Episode Director",
            "anime": {
                "mal_id": 1684,
                "url": "https://myanimelist.net/anime/1684/Dotto_Koni-chan",
                "image_url": "https://cdn.myanimelist.net/images/anime/1910/106998.jpg?s=28ef6c6275889a5054e640f11e7c9526",
                "name": "Dotto Koni-chan"
            }
        },
        {
            "position": "Assistant Director",
            "anime": {
                "mal_id": 1684,
                "url": "https://myanimelist.net/anime/1684/Dotto_Koni-chan",
                "image_url": "https://cdn.myanimelist.net/images/anime/1910/106998.jpg?s=28ef6c6275889a5054e640f11e7c9526",
                "name": "Dotto Koni-chan"
            }
        },
        {
            "position": "Episode Director",
            "anime": {
                "mal_id": 36144,
                "url": "https://myanimelist.net/anime/36144/Garo__Vanishing_Line",
                "image_url": "https://cdn.myanimelist.net/images/anime/10/88236.jpg?s=84339d74cc14faa306ef2d1adb397fc7",
                "name": "Garo: Vanishing Line"
            }
        },
        {
            "position": "Episode Director",
            "anime": {
                "mal_id": 379,
                "url": "https://myanimelist.net/anime/379/Heppoko_Jikken_Animation_Excel♥Saga",
                "image_url": "https://cdn.myanimelist.net/images/anime/1728/97423.jpg?s=0ff3d9d22521bceb4119ef4c816ae71e",
                "name": "Heppoko Jikken Animation Excel♥Saga"
            }
        },
        {
            "position": "Storyboard",
            "anime": {
                "mal_id": 379,
                "url": "https://myanimelist.net/anime/379/Heppoko_Jikken_Animation_Excel♥Saga",
                "image_url": "https://cdn.myanimelist.net/images/anime/1728/97423.jpg?s=0ff3d9d22521bceb4119ef4c816ae71e",
                "name": "Heppoko Jikken Animation Excel♥Saga"
            }
        },
        {
            "position": "Episode Director",
            "anime": {
                "mal_id": 360,
                "url": "https://myanimelist.net/anime/360/Himiko-den",
                "image_url": "https://cdn.myanimelist.net/images/anime/8/80544.jpg?s=cbd3f96251430f606ad2b4a8653a5f34",
                "name": "Himiko-den"
            }
        },
        {
            "position": "Episode Director",
            "anime": {
                "mal_id": 37972,
                "url": "https://myanimelist.net/anime/37972/Hoshiai_no_Sora",
                "image_url": "https://cdn.myanimelist.net/images/anime/1807/103081.jpg?s=41308fc8a21c9e882cc80f3ca3efc746",
                "name": "Hoshiai no Sora"
            }
        },
        {
            "position": "Assistant Director",
            "anime": {
                "mal_id": 37972,
                "url": "https://myanimelist.net/anime/37972/Hoshiai_no_Sora",
                "image_url": "https://cdn.myanimelist.net/images/anime/1807/103081.jpg?s=41308fc8a21c9e882cc80f3ca3efc746",
                "name": "Hoshiai no Sora"
            }
        },
        {
            "position": "Episode Director",
            "anime": {
                "mal_id": 33899,
                "url": "https://myanimelist.net/anime/33899/IDOLiSH7",
                "image_url": "https://cdn.myanimelist.net/images/anime/1390/90828.jpg?s=10d7069c20d978f703eb90ee7154ef67",
                "name": "IDOLiSH7"
            }
        },
        {
            "position": "Episode Director",
            "anime": {
                "mal_id": 1057,
                "url": "https://myanimelist.net/anime/1057/Ippatsu_Kiki_Musume",
                "image_url": "https://cdn.myanimelist.net/images/anime/6/34133.jpg?s=11402e362c9f0ca66870aa7eb2d5a055",
                "name": "Ippatsu Kiki Musume"
            }
        },
        {
            "position": "Storyboard",
            "anime": {
                "mal_id": 1057,
                "url": "https://myanimelist.net/anime/1057/Ippatsu_Kiki_Musume",
                "image_url": "https://cdn.myanimelist.net/images/anime/6/34133.jpg?s=11402e362c9f0ca66870aa7eb2d5a055",
                "name": "Ippatsu Kiki Musume"
            }
        },
        {
            "position": "Storyboard",
            "anime": {
                "mal_id": 427,
                "url": "https://myanimelist.net/anime/427/Kaleido_Star",
                "image_url": "https://cdn.myanimelist.net/images/anime/3/75487.jpg?s=a55f2888ba32746a835f971030ddfc8c",
                "name": "Kaleido Star"
            }
        },
        {
            "position": "Episode Director",
            "anime": {
                "mal_id": 427,
                "url": "https://myanimelist.net/anime/427/Kaleido_Star",
                "image_url": "https://cdn.myanimelist.net/images/anime/3/75487.jpg?s=a55f2888ba32746a835f971030ddfc8c",
                "name": "Kaleido Star"
            }
        },
        {
            "position": "Director",
            "anime": {
                "mal_id": 766,
                "url": "https://myanimelist.net/anime/766/Kishin_Houkou_Demonbane",
                "image_url": "https://cdn.myanimelist.net/images/anime/1/766.jpg?s=ab44b576513551e1f13e4f386635be10",
                "name": "Kishin Houkou Demonbane"
            }
        },
        {
            "position": "Episode Director",
            "anime": {
                "mal_id": 1374,
                "url": "https://myanimelist.net/anime/1374/Kyoushoku_Soukou_Guyver_2005",
                "image_url": "https://cdn.myanimelist.net/images/anime/6/3697.jpg?s=26c64daad037a135fa211d4e4e732739",
                "name": "Kyoushoku Soukou Guyver (2005)"
            }
        },
        {
            "position": "Storyboard",
            "anime": {
                "mal_id": 1374,
                "url": "https://myanimelist.net/anime/1374/Kyoushoku_Soukou_Guyver_2005",
                "image_url": "https://cdn.myanimelist.net/images/anime/6/3697.jpg?s=26c64daad037a135fa211d4e4e732739",
                "name": "Kyoushoku Soukou Guyver (2005)"
            }
        },
        {
            "position": "Episode Director",
            "anime": {
                "mal_id": 457,
                "url": "https://myanimelist.net/anime/457/Mushishi",
                "image_url": "https://cdn.myanimelist.net/images/anime/2/73862.jpg?s=aa50ffa32575c50c11cb2828b8776a0f",
                "name": "Mushishi"
            }
        },
        {
            "position": "Episode Director",
            "anime": {
                "mal_id": 31174,
                "url": "https://myanimelist.net/anime/31174/Osomatsu-san",
                "image_url": "https://cdn.myanimelist.net/images/anime/7/76540.jpg?s=1d4354fca47b9af39b34f2475a18ce5b",
                "name": "Osomatsu-san"
            }
        },
        {
            "position": "Episode Director",
            "anime": {
                "mal_id": 35067,
                "url": "https://myanimelist.net/anime/35067/Osomatsu-san_2nd_Season",
                "image_url": "https://cdn.myanimelist.net/images/anime/13/88328.jpg?s=385a5fcd729116c59d593fa769796317",
                "name": "Osomatsu-san 2nd Season"
            }
        },
        {
            "position": "Episode Director",
            "anime": {
                "mal_id": 32772,
                "url": "https://myanimelist.net/anime/32772/Puzzle___Dragons_Cross",
                "image_url": "https://cdn.myanimelist.net/images/anime/5/80793.jpg?s=b333a9f2d635059c629d95bcec94a886",
                "name": "Puzzle & Dragons Cross"
            }
        },
        {
            "position": "Key Animation",
            "anime": {
                "mal_id": 32772,
                "url": "https://myanimelist.net/anime/32772/Puzzle___Dragons_Cross",
                "image_url": "https://cdn.myanimelist.net/images/anime/5/80793.jpg?s=b333a9f2d635059c629d95bcec94a886",
                "name": "Puzzle & Dragons Cross"
            }
        },
        {
            "position": "Episode Director",
            "anime": {
                "mal_id": 205,
                "url": "https://myanimelist.net/anime/205/Samurai_Champloo",
                "image_url": "https://cdn.myanimelist.net/images/anime/11/29134.jpg?s=91eda11887314d6dc1921043c5d4e39e",
                "name": "Samurai Champloo"
            }
        },
        {
            "position": "Episode Director",
            "anime": {
                "mal_id": 1823,
                "url": "https://myanimelist.net/anime/1823/Shin_Hakkenden",
                "image_url": "https://cdn.myanimelist.net/images/anime/10/49801.jpg?s=e632e50115ea00716d586acb4ddc138a",
                "name": "Shin Hakkenden"
            }
        },
        {
            "position": "Episode Director",
            "anime": {
                "mal_id": 1618,
                "url": "https://myanimelist.net/anime/1618/Soreyuke_Uchuu_Senkan_Yamamoto_Yohko_1999",
                "image_url": "https://cdn.myanimelist.net/images/anime/5/30937.jpg?s=1b894fb0989ff4720b7291fc2874e0ba",
                "name": "Soreyuke! Uchuu Senkan Yamamoto Yohko (1999)"
            }
        },
        {
            "position": "Storyboard",
            "anime": {
                "mal_id": 1837,
                "url": "https://myanimelist.net/anime/1837/Sumeba_Miyako_no_Cosmos-sou_Suttoko_Taisen_Dokkoida",
                "image_url": "https://cdn.myanimelist.net/images/anime/8/84824.jpg?s=298047604e3ed5e1eb010b9a527b6b20",
                "name": "Sumeba Miyako no Cosmos-sou Suttoko Taisen Dokkoida"
            }
        },
        {
            "position": "Episode Director",
            "anime": {
                "mal_id": 1837,
                "url": "https://myanimelist.net/anime/1837/Sumeba_Miyako_no_Cosmos-sou_Suttoko_Taisen_Dokkoida",
                "image_url": "https://cdn.myanimelist.net/images/anime/8/84824.jpg?s=298047604e3ed5e1eb010b9a527b6b20",
                "name": "Sumeba Miyako no Cosmos-sou Suttoko Taisen Dokkoida"
            }
        },
        {
            "position": "Assistant Director",
            "anime": {
                "mal_id": 37430,
                "url": "https://myanimelist.net/anime/37430/Tensei_shitara_Slime_Datta_Ken",
                "image_url": "https://cdn.myanimelist.net/images/anime/1694/93337.jpg?s=348972deed419a80ce811f787556a515",
                "name": "Tensei shitara Slime Datta Ken"
            }
        },
        {
            "position": "Episode Director",
            "anime": {
                "mal_id": 37430,
                "url": "https://myanimelist.net/anime/37430/Tensei_shitara_Slime_Datta_Ken",
                "image_url": "https://cdn.myanimelist.net/images/anime/1694/93337.jpg?s=348972deed419a80ce811f787556a515",
                "name": "Tensei shitara Slime Datta Ken"
            }
        },
        {
            "position": "Episode Director",
            "anime": {
                "mal_id": 1048,
                "url": "https://myanimelist.net/anime/1048/The_SoulTaker__Tamashii-gari",
                "image_url": "https://cdn.myanimelist.net/images/anime/9/11004.jpg?s=c399c9621d6b0ce9a9683e63efbddec7",
                "name": "The SoulTaker: Tamashii-gari"
            }
        },
        {
            "position": "Storyboard",
            "anime": {
                "mal_id": 1048,
                "url": "https://myanimelist.net/anime/1048/The_SoulTaker__Tamashii-gari",
                "image_url": "https://cdn.myanimelist.net/images/anime/9/11004.jpg?s=c399c9621d6b0ce9a9683e63efbddec7",
                "name": "The SoulTaker: Tamashii-gari"
            }
        },
        {
            "position": "Storyboard",
            "anime": {
                "mal_id": 175,
                "url": "https://myanimelist.net/anime/175/Tokyo_Underground",
                "image_url": "https://cdn.myanimelist.net/images/anime/9/21036.jpg?s=f2d355c80a03c92a9f0302066a26fbe4",
                "name": "Tokyo Underground"
            }
        },
        {
            "position": "Episode Director",
            "anime": {
                "mal_id": 175,
                "url": "https://myanimelist.net/anime/175/Tokyo_Underground",
                "image_url": "https://cdn.myanimelist.net/images/anime/9/21036.jpg?s=f2d355c80a03c92a9f0302066a26fbe4",
                "name": "Tokyo Underground"
            }
        }
    ]
}