{
    "mal_id": 36161,
    "url": "https://myanimelist.net/people/36161/Shinichi_Tanimura",
    "image_url": "https://cdn.myanimelist.net/img/sp/icon/apple-touch-icon-256.png",
    "name": "Shinichi Tanimura",
    "given_name": "心一",
    "family_name": "谷村",
    "birthday": null,
    "member_favorites": 0,
    "voice_acting_roles": [],
    "anime_staff_positions": [
        {
            "position": "Art Director",
            "anime": {
                "mal_id": 366,
                "url": "https://myanimelist.net/anime/366/AIKa",
                "image_url": "https://cdn.myanimelist.net/images/anime/11/61673.jpg?s=2de3f17eeacefa449013910fb5914277",
                "name": "AIKa"
            }
        },
        {
            "position": "Art Director",
            "anime": {
                "mal_id": 17325,
                "url": "https://myanimelist.net/anime/17325/Ajin_Senshi",
                "image_url": "https://cdn.myanimelist.net/images/anime/12/46245.jpg?s=9288dc418b4e148c329d43ab9471cd7e",
                "name": "Ajin Senshi"
            }
        },
        {
            "position": "Background Art",
            "anime": {
                "mal_id": 17117,
                "url": "https://myanimelist.net/anime/17117/Aoi_Kioku__Manmou_Kaitaku_to_Shounen-tachi",
                "image_url": "https://cdn.myanimelist.net/images/anime/3/45755.jpg?s=555d01c6d27305883376cef4ffa5c191",
                "name": "Aoi Kioku: Manmou Kaitaku to Shounen-tachi"
            }
        },
        {
            "position": "Background Art",
            "anime": {
                "mal_id": 2622,
                "url": "https://myanimelist.net/anime/2622/Big_Wars__Kami_Utsu_Akaki_Kouya_ni",
                "image_url": "https://cdn.myanimelist.net/images/anime/3/72814.jpg?s=28ba183209673654d787fbe629566296",
                "name": "Big Wars: Kami Utsu Akaki Kouya ni"
            }
        },
        {
            "position": "Art Director",
            "anime": {
                "mal_id": 10681,
                "url": "https://myanimelist.net/anime/10681/Blood-C__The_Last_Dark",
                "image_url": "https://cdn.myanimelist.net/images/anime/1159/94216.jpg?s=decc38a59f751b2132a45933cd9af69f",
                "name": "Blood-C: The Last Dark"
            }
        },
        {
            "position": "Art Director",
            "anime": {
                "mal_id": 2142,
                "url": "https://myanimelist.net/anime/2142/Blue_Dragon",
                "image_url": "https://cdn.myanimelist.net/images/anime/2/20597.jpg?s=a8cffaadc89c115f724112a69cf1af07",
                "name": "Blue Dragon"
            }
        },
        {
            "position": "Art Director",
            "anime": {
                "mal_id": 4197,
                "url": "https://myanimelist.net/anime/4197/Blue_Dragon__Tenkai_no_Shichi_Ryuu",
                "image_url": "https://cdn.myanimelist.net/images/anime/2/21147.jpg?s=9d4814a21bcad55a7158425dd370c8c8",
                "name": "Blue Dragon: Tenkai no Shichi Ryuu"
            }
        },
        {
            "position": "Art Director",
            "anime": {
                "mal_id": 11867,
                "url": "https://myanimelist.net/anime/11867/Cipher",
                "image_url": "https://cdn.myanimelist.net/images/anime/11/33203.jpg?s=ab0371be59a6cae3389089460cb15355",
                "name": "Cipher"
            }
        },
        {
            "position": "Art Director",
            "anime": {
                "mal_id": 25731,
                "url": "https://myanimelist.net/anime/25731/Cross_Ange__Tenshi_to_Ryuu_no_Rondo",
                "image_url": "https://cdn.myanimelist.net/images/anime/2/67515.jpg?s=570bbe8db2ab9760af78d1471bfc3f9f",
                "name": "Cross Ange: Tenshi to Ryuu no Rondo"
            }
        },
        {
            "position": "Background Art",
            "anime": {
                "mal_id": 116,
                "url": "https://myanimelist.net/anime/116/El_Hazard__The_Wanderers",
                "image_url": "https://cdn.myanimelist.net/images/anime/13/24439.jpg?s=4144e87eeb4d2d7d7ac5866e7ba1a08b",
                "name": "El Hazard: The Wanderers"
            }
        },
        {
            "position": "Background Art",
            "anime": {
                "mal_id": 6702,
                "url": "https://myanimelist.net/anime/6702/Fairy_Tail",
                "image_url": "https://cdn.myanimelist.net/images/anime/5/18179.jpg?s=df96f46f0942261b7b962529b1cae778",
                "name": "Fairy Tail"
            }
        },
        {
            "position": "Background Art",
            "anime": {
                "mal_id": 1747,
                "url": "https://myanimelist.net/anime/1747/Freedom",
                "image_url": "https://cdn.myanimelist.net/images/anime/4/50511.jpg?s=47c9dc76d78fb4bbb7c2ca05dab8b3e5",
                "name": "Freedom"
            }
        },
        {
            "position": "Art Director",
            "anime": {
                "mal_id": 430,
                "url": "https://myanimelist.net/anime/430/Fullmetal_Alchemist__The_Conqueror_of_Shamballa",
                "image_url": "https://cdn.myanimelist.net/images/anime/1707/94039.jpg?s=f759bfb8aeb4c222719d13cc37de9a7f",
                "name": "Fullmetal Alchemist: The Conqueror of Shamballa"
            }
        },
        {
            "position": "Art Director",
            "anime": {
                "mal_id": 9135,
                "url": "https://myanimelist.net/anime/9135/Fullmetal_Alchemist__The_Sacred_Star_of_Milos",
                "image_url": "https://cdn.myanimelist.net/images/anime/2/29550.jpg?s=60b7cdadf0ac1a2cc1b1462d9792005a",
                "name": "Fullmetal Alchemist: The Sacred Star of Milos"
            }
        },
        {
            "position": "Background Art",
            "anime": {
                "mal_id": 3015,
                "url": "https://myanimelist.net/anime/3015/Ginga_Eiyuu_Densetsu_Gaiden__Ougon_no_Tsubasa",
                "image_url": "https://cdn.myanimelist.net/images/anime/7/52221.jpg?s=5174ec3a9e3b758307f2ace200df2070",
                "name": "Ginga Eiyuu Densetsu Gaiden: Ougon no Tsubasa"
            }
        },
        {
            "position": "Art Director",
            "anime": {
                "mal_id": 3016,
                "url": "https://myanimelist.net/anime/3016/Ginga_Eiyuu_Densetsu__Arata_Naru_Tatakai_no_Overture",
                "image_url": "https://cdn.myanimelist.net/images/anime/8/22498.jpg?s=8e76b70db63dd3dc83ac461dacd716f2",
                "name": "Ginga Eiyuu Densetsu: Arata Naru Tatakai no Overture"
            }
        },
        {
            "position": "Art Director",
            "anime": {
                "mal_id": 1082,
                "url": "https://myanimelist.net/anime/1082/Hikari_to_Mizu_no_Daphne",
                "image_url": "https://cdn.myanimelist.net/images/anime/7/49131.jpg?s=9133a42d455840166cf237c4b2d5f7ce",
                "name": "Hikari to Mizu no Daphne"
            }
        },
        {
            "position": "Art Director",
            "anime": {
                "mal_id": 581,
                "url": "https://myanimelist.net/anime/581/Honoo_no_Labyrinth",
                "image_url": "https://cdn.myanimelist.net/images/anime/3/20329.jpg?s=5dfcb4432291753b65a8761a796a7a0a",
                "name": "Honoo no Labyrinth"
            }
        },
        {
            "position": "Background Art",
            "anime": {
                "mal_id": 15377,
                "url": "https://myanimelist.net/anime/15377/Hyakka_Ryouran__Samurai_Bride",
                "image_url": "https://cdn.myanimelist.net/images/anime/5/45248.jpg?s=1d9e73ee12c13900300e9a6882a70f65",
                "name": "Hyakka Ryouran: Samurai Bride"
            }
        },
        {
            "position": "Art Director",
            "anime": {
                "mal_id": 1947,
                "url": "https://myanimelist.net/anime/1947/Kikou_Sennyo_Rouran",
                "image_url": "https://cdn.myanimelist.net/images/anime/5/22629.jpg?s=92930bed31d5deac2dbebc5948fda6c9",
                "name": "Kikou Sennyo Rouran"
            }
        },
        {
            "position": "Art Director",
            "anime": {
                "mal_id": 17563,
                "url": "https://myanimelist.net/anime/17563/Koutetsu_no_Vendetta_Episode_0",
                "image_url": "https://cdn.myanimelist.net/images/anime/10/51987.jpg?s=0fcd8cc097f02857993a5ab44793019c",
                "name": "Koutetsu no Vendetta Episode 0"
            }
        },
        {
            "position": "Background Art",
            "anime": {
                "mal_id": 7598,
                "url": "https://myanimelist.net/anime/7598/Loups_Garous",
                "image_url": "https://cdn.myanimelist.net/images/anime/13/26343.jpg?s=18d92ae47b44ca977e294d52756aaac6",
                "name": "Loups=Garous"
            }
        },
        {
            "position": "Background Art",
            "anime": {
                "mal_id": 6115,
                "url": "https://myanimelist.net/anime/6115/Lupin_III_vs_Detective_Conan",
                "image_url": "https://cdn.myanimelist.net/images/anime/11/27602.jpg?s=3cbb2e544be926539d255a7a928d8b80",
                "name": "Lupin III vs. Detective Conan"
            }
        },
        {
            "position": "Art Director",
            "anime": {
                "mal_id": 3654,
                "url": "https://myanimelist.net/anime/3654/Macademi_Wasshoi",
                "image_url": "https://cdn.myanimelist.net/images/anime/10/74031.jpg?s=bc321651b295b5b18c5d0c8269ff9227",
                "name": "Macademi Wasshoi!"
            }
        },
        {
            "position": "Background Art",
            "anime": {
                "mal_id": 3448,
                "url": "https://myanimelist.net/anime/3448/Mad★Bull_34",
                "image_url": "https://cdn.myanimelist.net/images/anime/8/67821.jpg?s=602dbe7fe7f413ef756d65e0e53bf49c",
                "name": "Mad★Bull 34"
            }
        },
        {
            "position": "Background Art",
            "anime": {
                "mal_id": 14527,
                "url": "https://myanimelist.net/anime/14527/Medaka_Box_Abnormal",
                "image_url": "https://cdn.myanimelist.net/images/anime/11/62919.jpg?s=63e0843de6e61eb8d5f18dd3efd1a5de",
                "name": "Medaka Box Abnormal"
            }
        },
        {
            "position": "Background Art",
            "anime": {
                "mal_id": 87,
                "url": "https://myanimelist.net/anime/87/Mobile_Suit_Gundam__Chars_Counterattack",
                "image_url": "https://cdn.myanimelist.net/images/anime/1523/92371.jpg?s=e2903b38ee122bcf17544749f6c9a8ac",
                "name": "Mobile Suit Gundam: Char's Counterattack"
            }
        },
        {
            "position": "Art Director",
            "anime": {
                "mal_id": 1287,
                "url": "https://myanimelist.net/anime/1287/Odin__Koushi_Hansen_Starlight",
                "image_url": "https://cdn.myanimelist.net/images/anime/11/72878.jpg?s=372cb194cc46b5aa2beb79f6ad98d643",
                "name": "Odin: Koushi Hansen Starlight"
            }
        },
        {
            "position": "Art Director",
            "anime": {
                "mal_id": 12859,
                "url": "https://myanimelist.net/anime/12859/One_Piece_Film__Z",
                "image_url": "https://cdn.myanimelist.net/images/anime/6/44297.jpg?s=02de30b90ef043d93691aa6a3c1a0d2a",
                "name": "One Piece Film: Z"
            }
        },
        {
            "position": "Background Art",
            "anime": {
                "mal_id": 20159,
                "url": "https://myanimelist.net/anime/20159/Pokemon__The_Origin",
                "image_url": "https://cdn.myanimelist.net/images/anime/7/53701.jpg?s=6eb43344cf1149fe699c1cddf4d305b3",
                "name": "Pokemon: The Origin"
            }
        },
        {
            "position": "Art Director",
            "anime": {
                "mal_id": 208,
                "url": "https://myanimelist.net/anime/208/ROD__Read_or_Die",
                "image_url": "https://cdn.myanimelist.net/images/anime/1/208.jpg?s=a499270f9e60345d3adbfe558e8ae20f",
                "name": "R.O.D: Read or Die"
            }
        },
        {
            "position": "Background Art",
            "anime": {
                "mal_id": 100,
                "url": "https://myanimelist.net/anime/100/Shin_Shirayuki-hime_Densetsu_Prétear",
                "image_url": "https://cdn.myanimelist.net/images/anime/9/11709.jpg?s=7775b5ae6e2a6ad2b66ea69762502f86",
                "name": "Shin Shirayuki-hime Densetsu Prétear"
            }
        },
        {
            "position": "Art Director",
            "anime": {
                "mal_id": 342,
                "url": "https://myanimelist.net/anime/342/Starship_Operators",
                "image_url": "https://cdn.myanimelist.net/images/anime/9/21303.jpg?s=ff98c72fee9b09286d1f8a356a1fdf49",
                "name": "Starship Operators"
            }
        },
        {
            "position": "Art Director",
            "anime": {
                "mal_id": 25,
                "url": "https://myanimelist.net/anime/25/Sunabouzu",
                "image_url": "https://cdn.myanimelist.net/images/anime/6/75536.jpg?s=3638129c80bb09b1cc49b582dc934fa9",
                "name": "Sunabouzu"
            }
        },
        {
            "position": "Background Art",
            "anime": {
                "mal_id": 182,
                "url": "https://myanimelist.net/anime/182/Tenkuu_no_Escaflowne",
                "image_url": "https://cdn.myanimelist.net/images/anime/5/30689.jpg?s=dec965692399fb8214ba850ed4bcb965",
                "name": "Tenkuu no Escaflowne"
            }
        },
        {
            "position": "Background Art",
            "anime": {
                "mal_id": 17437,
                "url": "https://myanimelist.net/anime/17437/The_iDOLMSTER_Movie__Kagayaki_no_Mukougawa_e",
                "image_url": "https://cdn.myanimelist.net/images/anime/2/71801.jpg?s=a9350b49412b06efafa79409b58ad86b",
                "name": "The iDOLM@STER Movie: Kagayaki no Mukougawa e!"
            }
        },
        {
            "position": "Background Art",
            "anime": {
                "mal_id": 1048,
                "url": "https://myanimelist.net/anime/1048/The_SoulTaker__Tamashii-gari",
                "image_url": "https://cdn.myanimelist.net/images/anime/9/11004.jpg?s=c399c9621d6b0ce9a9683e63efbddec7",
                "name": "The SoulTaker: Tamashii-gari"
            }
        },
        {
            "position": "Art Director",
            "anime": {
                "mal_id": 4484,
                "url": "https://myanimelist.net/anime/4484/Umi_no_Yami_Tsuki_no_Kage",
                "image_url": "https://cdn.myanimelist.net/images/anime/13/37269.jpg?s=ccc4e0b6fea8c8486cc5644345792a9c",
                "name": "Umi no Yami, Tsuki no Kage"
            }
        },
        {
            "position": "Background Art",
            "anime": {
                "mal_id": 1112,
                "url": "https://myanimelist.net/anime/1112/Vandread__Taidou-hen",
                "image_url": "https://cdn.myanimelist.net/images/anime/10/75448.jpg?s=9b4add94144935d0469f5f8b766e803d",
                "name": "Vandread: Taidou-hen"
            }
        },
        {
            "position": "Art Director",
            "anime": {
                "mal_id": 20053,
                "url": "https://myanimelist.net/anime/20053/Wizard_Barristers__Benmashi_Cecil",
                "image_url": "https://cdn.myanimelist.net/images/anime/9/58145.jpg?s=943a44b55f37e130dbc72da27436cfab",
                "name": "Wizard Barristers: Benmashi Cecil"
            }
        },
        {
            "position": "Art Director",
            "anime": {
                "mal_id": 3778,
                "url": "https://myanimelist.net/anime/3778/Yuukan_Club",
                "image_url": "https://cdn.myanimelist.net/images/anime/7/73828.jpg?s=aa0b233b917592db1a2687f4b02008c4",
                "name": "Yuukan Club"
            }
        },
        {
            "position": "Art Director",
            "anime": {
                "mal_id": 17681,
                "url": "https://myanimelist.net/anime/17681/Zettai_Bouei_Leviathan",
                "image_url": "https://cdn.myanimelist.net/images/anime/13/47499.jpg?s=e2f2df3477dee6ab1d048cf7778d169b",
                "name": "Zettai Bouei Leviathan"
            }
        },
        {
            "position": "Art Director",
            "anime": {
                "mal_id": 712,
                "url": "https://myanimelist.net/anime/712/Zoids_Genesis",
                "image_url": "https://cdn.myanimelist.net/images/anime/1906/109746.jpg?s=bb0050019a4a689860807b311de41567",
                "name": "Zoids Genesis"
            }
        }
    ]
}