{
    "mal_id": 28037,
    "url": "https://myanimelist.net/people/28037/Cinema_Staff",
    "image_url": "https://cdn.myanimelist.net/images/voiceactors/1/29643.jpg",
    "name": "Cinema Staff",
    "given_name": null,
    "family_name": null,
    "birthday": null,
    "member_favorites": 31,
    "voice_acting_roles": [],
    "anime_staff_positions": [
        {
            "position": "Theme Song Performance",
            "anime": {
                "mal_id": 16498,
                "url": "https://myanimelist.net/anime/16498/Shingeki_no_Kyojin",
                "image_url": "https://cdn.myanimelist.net/images/anime/10/47347.jpg?s=119cefa0efd1ee46e9a91bba1a46eaa5",
                "name": "Shingeki no Kyojin"
            }
        },
        {
            "position": "Theme Song Performance",
            "anime": {
                "mal_id": 38524,
                "url": "https://myanimelist.net/anime/38524/Shingeki_no_Kyojin_Season_3_Part_2",
                "image_url": "https://cdn.myanimelist.net/images/anime/1517/100633.jpg?s=b0a77a1da1ec8e50a1b603ad43c24a03",
                "name": "Shingeki no Kyojin Season 3 Part 2"
            }
        },
        {
            "position": "Theme Song Performance",
            "anime": {
                "mal_id": 25781,
                "url": "https://myanimelist.net/anime/25781/Shingeki_no_Kyojin__Kuinaki_Sentaku",
                "image_url": "https://cdn.myanimelist.net/images/anime/8/69497.jpg?s=7dc1d732aaeb1ab31d7d31fe6371476f",
                "name": "Shingeki no Kyojin: Kuinaki Sentaku"
            }
        },
        {
            "position": "Theme Song Performance",
            "anime": {
                "mal_id": 21639,
                "url": "https://myanimelist.net/anime/21639/Yu☆Gi☆Oh_Arc-V",
                "image_url": "https://cdn.myanimelist.net/images/anime/10/62939.jpg?s=865692178fba591c16b3751b4c97d750",
                "name": "Yu☆Gi☆Oh! Arc-V"
            }
        }
    ]
}