{
    "mal_id": 40655,
    "url": "https://myanimelist.net/people/40655/Kazuko_Kikuchi",
    "image_url": "https://cdn.myanimelist.net/img/sp/icon/apple-touch-icon-256.png",
    "name": "Kazuko Kikuchi",
    "given_name": "和子",
    "family_name": "菊地",
    "birthday": null,
    "member_favorites": 0,
    "voice_acting_roles": [],
    "anime_staff_positions": [
        {
            "position": "Color Design",
            "anime": {
                "mal_id": 31964,
                "url": "https://myanimelist.net/anime/31964/Boku_no_Hero_Academia",
                "image_url": "https://cdn.myanimelist.net/images/anime/10/78745.jpg?s=20f73cb3af8f70ee17f155e525e809e8",
                "name": "Boku no Hero Academia"
            }
        },
        {
            "position": "Color Design",
            "anime": {
                "mal_id": 33486,
                "url": "https://myanimelist.net/anime/33486/Boku_no_Hero_Academia_2nd_Season",
                "image_url": "https://cdn.myanimelist.net/images/anime/12/85221.jpg?s=99905c9c0a721332cdb230444ce44dc9",
                "name": "Boku no Hero Academia 2nd Season"
            }
        },
        {
            "position": "Color Design",
            "anime": {
                "mal_id": 2759,
                "url": "https://myanimelist.net/anime/2759/Evangelion__10_You_Are_Not_Alone",
                "image_url": "https://cdn.myanimelist.net/images/anime/7/74975.jpg?s=0b67af75f2a2ea439d3d90958df219ae",
                "name": "Evangelion: 1.0 You Are (Not) Alone"
            }
        },
        {
            "position": "Color Design",
            "anime": {
                "mal_id": 3784,
                "url": "https://myanimelist.net/anime/3784/Evangelion__20_You_Can_Not_Advance",
                "image_url": "https://cdn.myanimelist.net/images/anime/5/74983.jpg?s=8556ecfcdc3985b259cc0ebb33b59a6b",
                "name": "Evangelion: 2.0 You Can (Not) Advance"
            }
        },
        {
            "position": "Color Design",
            "anime": {
                "mal_id": 3785,
                "url": "https://myanimelist.net/anime/3785/Evangelion__30_You_Can_Not_Redo",
                "image_url": "https://cdn.myanimelist.net/images/anime/9/43201.jpg?s=168dbb42694752d23854724941036e8c",
                "name": "Evangelion: 3.0 You Can (Not) Redo"
            }
        },
        {
            "position": "Color Design",
            "anime": {
                "mal_id": 3786,
                "url": "https://myanimelist.net/anime/3786/Evangelion__30_10_Thrice_Upon_a_Time",
                "image_url": "https://cdn.myanimelist.net/images/anime/1421/110903.jpg?s=743fc693bd225b16951b6974ab32ed8f",
                "name": "Evangelion: 3.0+1.0 Thrice Upon a Time"
            }
        },
        {
            "position": "Color Setting",
            "anime": {
                "mal_id": 3786,
                "url": "https://myanimelist.net/anime/3786/Evangelion__30_10_Thrice_Upon_a_Time",
                "image_url": "https://cdn.myanimelist.net/images/anime/1421/110903.jpg?s=743fc693bd225b16951b6974ab32ed8f",
                "name": "Evangelion: 3.0+1.0 Thrice Upon a Time"
            }
        },
        {
            "position": "Color Design",
            "anime": {
                "mal_id": 8097,
                "url": "https://myanimelist.net/anime/8097/Lupin_III__The_Last_Job",
                "image_url": "https://cdn.myanimelist.net/images/anime/2/21995.jpg?s=2973beb1c182873a99a57046704b6e22",
                "name": "Lupin III: The Last Job"
            }
        },
        {
            "position": "Color Design",
            "anime": {
                "mal_id": 28149,
                "url": "https://myanimelist.net/anime/28149/Nihon_Animator_Mihonichi",
                "image_url": "https://cdn.myanimelist.net/images/anime/11/71901.jpg?s=8e55c2cd9afe9385cf2d91389f42724a",
                "name": "Nihon Animator Mihonichi"
            }
        },
        {
            "position": "Color Setting",
            "anime": {
                "mal_id": 28149,
                "url": "https://myanimelist.net/anime/28149/Nihon_Animator_Mihonichi",
                "image_url": "https://cdn.myanimelist.net/images/anime/11/71901.jpg?s=8e55c2cd9afe9385cf2d91389f42724a",
                "name": "Nihon Animator Mihonichi"
            }
        },
        {
            "position": "Color Design",
            "anime": {
                "mal_id": 10161,
                "url": "https://myanimelist.net/anime/10161/No6",
                "image_url": "https://cdn.myanimelist.net/images/anime/1474/90768.jpg?s=482dfcab42dd8714087f6f837242180c",
                "name": "No.6"
            }
        },
        {
            "position": "Color Design",
            "anime": {
                "mal_id": 758,
                "url": "https://myanimelist.net/anime/758/RahXephon__Tagen_Hensoukyoku",
                "image_url": "https://cdn.myanimelist.net/images/anime/1771/94881.jpg?s=29a7afecb8b7614bf3e26f26b8014063",
                "name": "RahXephon: Tagen Hensoukyoku"
            }
        },
        {
            "position": "Color Design",
            "anime": {
                "mal_id": 5485,
                "url": "https://myanimelist.net/anime/5485/Shin_Mazinger_Shougeki_Z-hen",
                "image_url": "https://cdn.myanimelist.net/images/anime/1022/92865.jpg?s=4605992daff9096f29c4c39554c25403",
                "name": "Shin Mazinger Shougeki! Z-hen"
            }
        },
        {
            "position": "Color Design",
            "anime": {
                "mal_id": 21507,
                "url": "https://myanimelist.net/anime/21507/Soul_Eater_NOT",
                "image_url": "https://cdn.myanimelist.net/images/anime/8/61889.jpg?s=bb92d58d8130a6d4a1758ee6372f4d42",
                "name": "Soul Eater NOT!"
            }
        },
        {
            "position": "Color Design",
            "anime": {
                "mal_id": 1541,
                "url": "https://myanimelist.net/anime/1541/Souten_no_Ken",
                "image_url": "https://cdn.myanimelist.net/images/anime/12/17056.jpg?s=a2c2339d94bffd9874a719c1fad078a1",
                "name": "Souten no Ken"
            }
        },
        {
            "position": "Color Design",
            "anime": {
                "mal_id": 10005,
                "url": "https://myanimelist.net/anime/10005/Tetsujin_28-gou__Hakuchuu_no_Zangetsu",
                "image_url": "https://cdn.myanimelist.net/images/anime/7/27668.jpg?s=ee22073d9f20400af4ecc96dec1dda53",
                "name": "Tetsujin 28-gou: Hakuchuu no Zangetsu"
            }
        }
    ]
}