{
    "mal_id": 10916,
    "url": "https://myanimelist.net/anime/10916/Pokemon__Pikachu_no_Fuyuyasumi_2000",
    "image_url": "https://cdn.myanimelist.net/images/anime/1910/108234.jpg",
    "title": "Pokemon: Pikachu no Fuyuyasumi (2000)",
    "title_english": "Pokemon: Pikachu's Winter Vacation (2000)",
    "title_japanese": "ピカチュウのふゆやすみ2000",
    "type": "OVA",
    "source": "Game",
    "episodes": 2,
    "status": "Finished Airing",
    "aired": {
        "from": "1999-12-22T00:00:00+00:00",
        "to": null,
        "prop": {
            "from": {
                "day": 22,
                "month": 12,
                "year": 1999
            },
            "to": {
                "day": null,
                "month": null,
                "year": null
            }
        },
        "string": "Dec 22, 1999"
    },
    "score": 6.43,
    "scored_by": 3485,
    "rank": 6247,
    "popularity": 5454,
    "members": 7614,
    "favorites": 2,
    "premiered": null,
    "studios": [
        {
            "mal_id": 28,
            "type": "anime",
            "name": "OLM",
            "url": "https://myanimelist.net/anime/producer/28/OLM"
        }
    ]
}