{
    "mal_id": 508,
    "url": "https://myanimelist.net/anime/508/Tottoko_Hamtarou",
    "image_url": "https://cdn.myanimelist.net/images/anime/3/21562.jpg",
    "title": "Tottoko Hamtarou",
    "title_english": "Hamtaro",
    "title_japanese": "とっとこハム太郎",
    "type": "TV",
    "source": "Manga",
    "episodes": 296,
    "status": "Finished Airing",
    "aired": {
        "from": "2000-07-07T00:00:00+00:00",
        "to": "2006-03-31T00:00:00+00:00",
        "prop": {
            "from": {
                "day": 7,
                "month": 7,
                "year": 2000
            },
            "to": {
                "day": 31,
                "month": 3,
                "year": 2006
            }
        },
        "string": "Jul 7, 2000 to Mar 31, 2006"
    },
    "score": 6.97,
    "scored_by": 17493,
    "rank": 3757,
    "popularity": 2358,
    "members": 46113,
    "favorites": 237,
    "premiered": "Summer 2000",
    "studios": [
        {
            "mal_id": 73,
            "type": "anime",
            "name": "TMS Entertainment",
            "url": "https://myanimelist.net/anime/producer/73/TMS_Entertainment"
        }
    ]
}