{
    "mal_id": 6467,
    "url": "https://myanimelist.net/anime/6467/Detective_Conan_Movie_14__The_Lost_Ship_in_the_Sky",
    "image_url": "https://cdn.myanimelist.net/images/anime/7/22312.jpg",
    "title": "Detective Conan Movie 14: The Lost Ship in the Sky",
    "title_english": null,
    "title_japanese": "名探偵コナン 天空の難破船",
    "type": "Movie",
    "source": "Manga",
    "episodes": 1,
    "status": "Finished Airing",
    "aired": {
        "from": "2010-04-17T00:00:00+00:00",
        "to": null,
        "prop": {
            "from": {
                "day": 17,
                "month": 4,
                "year": 2010
            },
            "to": {
                "day": null,
                "month": null,
                "year": null
            }
        },
        "string": "Apr 17, 2010"
    },
    "score": 8.15,
    "scored_by": 24463,
    "rank": 361,
    "popularity": 2468,
    "members": 42329,
    "favorites": 52,
    "premiered": null,
    "studios": [
        {
            "mal_id": 65,
            "type": "anime",
            "name": "Tokyo Movie Shinsha",
            "url": "https://myanimelist.net/anime/producer/65/Tokyo_Movie_Shinsha"
        }
    ]
}